scr/FDTD_Acoustic_2D.py
scr/__init__.py
Nevia_ArashRezaei-0.1.dist-info/LICENSE
Nevia_ArashRezaei-0.1.dist-info/METADATA
Nevia_ArashRezaei-0.1.dist-info/WHEEL
Nevia_ArashRezaei-0.1.dist-info/top_level.txt
Nevia_ArashRezaei-0.1.dist-info/RECORD
