Metadata-Version: 2.1
Name: Nevia-ArashRezaei
Version: 0.1
Summary: Forward Modeling of Wave Propagation
Home-page: https://github.com/ArashRezaei/Nevia
Author: Arash Rezaei Nevisi
Author-email: Arash Rezaei Nevisi <arashrezaei96@gmail.com>
License: MIT
Project-URL: Homepage, https://github.com/ArashRezaei/Nevia
Project-URL: Bug Tracker, https://github.com/ArashRezaei/Nevia/issues
Platform: UNKNOWN
Classifier: Programming Language :: Python :: 3
Classifier: License :: OSI Approved :: MIT License
Classifier: Operating System :: OS Independent
Requires-Python: >=3.7
License-File: LICENSE
Requires-Dist: matplotlib
Requires-Dist: numpy
Requires-Dist: scipy
Requires-Dist: screeninfo
